{
  "6Wpj1RUs1hBwKuAzfFPGeHtgiQp5Fx4PVkDwfgzkLYCu": {
    "active": [
      {
        "event": {
          "owner": "6Wpj1RUs1hBwKuAzfFPGeHtgiQp5Fx4PVkDwfgzkLYCu",
          "pool": "HRgVv1pyBLXdsAddq4ubSqo8xdQWRrYbvmXqEDtectce",
          "id": "0d",
          "liquidity": "0454a2da9d00",
          "lowerTick": -13900,
          "upperTick": -13880,
          "currentTimestamp": "67615f9a",
          "secondsPerLiquidityInsideInitial": "117cbf42bf8bdfa8"
        },
        "points": "76b8688b00"
      },
      {
        "event": {
          "owner": "6Wpj1RUs1hBwKuAzfFPGeHtgiQp5Fx4PVkDwfgzkLYCu",
          "pool": "HRgVv1pyBLXdsAddq4ubSqo8xdQWRrYbvmXqEDtectce",
          "id": "0c",
          "liquidity": "0454a2da9d00",
          "lowerTick": -13900,
          "upperTick": -13880,
          "currentTimestamp": "67615f96",
          "secondsPerLiquidityInsideInitial": "0ba87f81d507ea70"
        },
        "points": "7b60805300"
      },
      {
        "event": {
          "owner": "6Wpj1RUs1hBwKuAzfFPGeHtgiQp5Fx4PVkDwfgzkLYCu",
          "pool": "HRgVv1pyBLXdsAddq4ubSqo8xdQWRrYbvmXqEDtectce",
          "id": "0b",
          "liquidity": "0454a2da9d00",
          "lowerTick": -13900,
          "upperTick": -13880,
          "currentTimestamp": "67615f92",
          "secondsPerLiquidityInsideInitial": "00"
        },
        "points": "84b0afe300"
      }
    ],
    "closed": []
  }
}