[
  {
    "address": "14NfRBBhPiKcRg9MBWvgjHfuZ2QcZf4gj1iTTYXpBDo6",
    "rank": 1,
    "last24hPoints": "43c96d39ec00",
    "points": "43c96d39ec00",
    "positions": 3
  },
  {
    "address": "2g2xzcMiTGysNZzv9zZcDqx7MtdRxWG1VHMVPDw3qdW9",
    "rank": 2,
    "last24hPoints": "2fa0f1eb4300",
    "points": "2fa0f1eb4300",
    "positions": 2
  },
  {
    "address": "GzH4Br9mHeBK7dbH8QmB3CCdNS753ctvcX6cRZQDAEYE",
    "rank": 3,
    "last24hPoints": "2ea795582d00",
    "points": "2ea795582d00",
    "positions": 1
  },
  {
    "address": "G1xQ78d2uc7VyCWg6MVhi66UMH7hGbVBFes6NLKfyDHQ",
    "rank": 4,
    "last24hPoints": "2ce44f9f3700",
    "points": "2ce44f9f3700",
    "positions": 2
  },
  {
    "address": "EQcxNEw2L6zdpSYKpSABGB2msgMPDLtG8ERubFAbPamZ",
    "rank": 5,
    "last24hPoints": "2397d9bbd700",
    "points": "2397d9bbd700",
    "positions": 3
  },
  {
    "address": "9MGSJXZwta7rWkL5MwpEbvwznXY6pU7uQqcoJoK2n39",
    "rank": 6,
    "last24hPoints": "218499d0d600",
    "points": "218499d0d600",
    "positions": 1
  },
  {
    "address": "udeseBsAkEHGRVdbsqNe9YKFDqcjn7iD9G5CP3LnA5Y",
    "rank": 7,
    "last24hPoints": "1cbef03ea000",
    "points": "1cbef03ea000",
    "positions": 1
  },
  {
    "address": "9zMoHSrefhQdwTXfwp7uTaXZ4mkSJszvJkVDSmKaxKy2",
    "rank": 8,
    "last24hPoints": "129f46fbb100",
    "points": "129f46fbb100",
    "positions": 1
  },
  {
    "address": "CQmeETMuzeotHzCa66Z71CVFUuD9arzK7ePx1ZH5Un5s",
    "rank": 9,
    "last24hPoints": "1155b49bc600",
    "points": "1155b49bc600",
    "positions": 0
  },
  {
    "address": "Fo8eXAo8jSvSZoTtNhdzES9zLqDjVeLYkEGYr6ULwRD1",
    "rank": 10,
    "last24hPoints": "0f9c1284ae00",
    "points": "0f9c1284ae00",
    "positions": 1
  },
  {
    "address": "5MR6sCjbHu8TCM3AUGcBbrr6ZUrwqRYmtysXQUB8826F",
    "rank": 11,
    "last24hPoints": "0d4d5b92f300",
    "points": "0d4d5b92f300",
    "positions": 1
  },
  {
    "address": "BHKcEoxm3uij2HSMBiDrFBAzHU84fSdq97abQFbHrRNe",
    "rank": 12,
    "last24hPoints": "0d1fa138c700",
    "points": "0d1fa138c700",
    "positions": 1
  },
  {
    "address": "Fn22zYkDLqM19a1rmfv6srKHVttBLeCx76Csiowawknx",
    "rank": 13,
    "last24hPoints": "0b00c3083300",
    "points": "0b00c3083300",
    "positions": 2
  },
  {
    "address": "89ocx1H5mMUsYdVjPNhdJwJrs2kJ6SdwUo4AyLzhxhkF",
    "rank": 14,
    "last24hPoints": "0a06a7b8fd00",
    "points": "0a06a7b8fd00",
    "positions": 1
  },
  {
    "address": "GdWUBzQCfLg8aUcQcDvEHMLaRpjr56cLfMLy5A3LhtqJ",
    "rank": 15,
    "last24hPoints": "099b7bb46200",
    "points": "099b7bb46200",
    "positions": 2
  },
  {
    "address": "9eEwkxasCYkKxsU6AvEc3U8AfaoX59RYRTKiVPHeJwfs",
    "rank": 16,
    "last24hPoints": "0989c9c06a00",
    "points": "0989c9c06a00",
    "positions": 1
  },
  {
    "address": "4VW2eQa6mpes5yG4sq3FAN6JjLZeF8pkpLvmEkgGqwTf",
    "rank": 17,
    "last24hPoints": "096ff1a2d400",
    "points": "096ff1a2d400",
    "positions": 1
  },
  {
    "address": "BaUfiMAxuW6xiLrxEfxHRF9v1ScoqaqZhuAK44cVrWh5",
    "rank": 18,
    "last24hPoints": "0956ba73f900",
    "points": "0956ba73f900",
    "positions": 1
  },
  {
    "address": "4yohwbfemHATENEnoVibtwB5UyXLwssMX2rb675biChT",
    "rank": 19,
    "last24hPoints": "092cb3d08c00",
    "points": "092cb3d08c00",
    "positions": 1
  },
  {
    "address": "EzTR6Dh3ZzKNoXtfCa3AbqWeoATT6gD9zoiEK7waBGW3",
    "rank": 20,
    "last24hPoints": "08d2aab2d100",
    "points": "08d2aab2d100",
    "positions": 1
  },
  {
    "address": "Bb51W8bz6CHjrd7a7edxGTt5PL3XQU2YeByE3qP46B5U",
    "rank": 21,
    "last24hPoints": "080b1b8eb600",
    "points": "080b1b8eb600",
    "positions": 1
  },
  {
    "address": "8kYdFcmLJWGKi3mV75g4qMXWGZBkfoKu114qStx5pAVM",
    "rank": 22,
    "last24hPoints": "07891852e600",
    "points": "07891852e600",
    "positions": 0
  },
  {
    "address": "7wxz2Dx4isPAG7ntsoGbdG7NK2joduHDJj7tciqQz1G1",
    "rank": 23,
    "last24hPoints": "062766e86f00",
    "points": "062766e86f00",
    "positions": 1
  },
  {
    "address": "BiDyMPhCE8Mz8X8CyGjEXkYLqT4X6s8fwio9D1PyRpdD",
    "rank": 24,
    "last24hPoints": "0616d30ea700",
    "points": "0616d30ea700",
    "positions": 1
  },
  {
    "address": "63CQPyL9xzCSy4ejNuqxxqfjRpAGVKa1KbJUvXfRSKZK",
    "rank": 25,
    "last24hPoints": "05da7f7e6800",
    "points": "05da7f7e6800",
    "positions": 1
  },
  {
    "address": "7x8tgkr5gujWpbZxWXvJ5YJuprbsLh8ZE6hyU2ubesES",
    "rank": 26,
    "last24hPoints": "05d6c5d1c800",
    "points": "05d6c5d1c800",
    "positions": 1
  },
  {
    "address": "JBpEJ3xH6vfJSRGx4R4bnkoUwEFmWZVDegG6pqHV8PqM",
    "rank": 27,
    "last24hPoints": "05b37fb73d00",
    "points": "05b37fb73d00",
    "positions": 1
  },
  {
    "address": "CQbM3M1fr1TgBvw42YjVJU1kKfwT3PvsaSCQWuLchLSa",
    "rank": 28,
    "last24hPoints": "05757effb600",
    "points": "05757effb600",
    "positions": 1
  },
  {
    "address": "G9Uxot5hbRUZ4tLQWDMg755coTVB5pG95f1k5BmsxKDy",
    "rank": 29,
    "last24hPoints": "051290fc3d00",
    "points": "051290fc3d00",
    "positions": 1
  },
  {
    "address": "8XzDo7wa2DEKhZ3ZUPbKykDvuYpAbFBkoZx3MoPVmGdA",
    "rank": 30,
    "last24hPoints": "04e087f27800",
    "points": "04e087f27800",
    "positions": 1
  },
  {
    "address": "8rjrujBJtSvdtmWSZ2qDRQkVxZnyhSrijs3iLHqzxjHG",
    "rank": 31,
    "last24hPoints": "049d8bb0db00",
    "points": "049d8bb0db00",
    "positions": 1
  },
  {
    "address": "6HU3wvAdya83VNDLtKLCtwAhNzs6MHoQQwf6Wz71HSoU",
    "rank": 32,
    "last24hPoints": "048c2d2f3100",
    "points": "048c2d2f3100",
    "positions": 1
  },
  {
    "address": "DkqrTXvCfYZnf7BsMMJDbXKkJ3gwWgL3CLsAkzCvXZdD",
    "rank": 33,
    "last24hPoints": "0479b6893800",
    "points": "0479b6893800",
    "positions": 1
  },
  {
    "address": "BASxt3BqTxrd6Wh14cQvUbZSr2j4opzoqCy9H9B52ysB",
    "rank": 34,
    "last24hPoints": "0436f5e26500",
    "points": "0436f5e26500",
    "positions": 1
  },
  {
    "address": "oJWNcxHR1GbDKydNNNM1db7aQMP7QxGuBs7FnDUuGNa",
    "rank": 35,
    "last24hPoints": "03f67d5bb400",
    "points": "03f67d5bb400",
    "positions": 1
  },
  {
    "address": "E8sT4mSPkC9WF3B8PCv3koLwvvKGq5zknjJCmpmfhARs",
    "rank": 36,
    "last24hPoints": "03d27e7aea00",
    "points": "03d27e7aea00",
    "positions": 1
  },
  {
    "address": "opbEyXWuKxjTBJpjm7qHfmbBaKDwUj2Z7rUiob4EBFf",
    "rank": 37,
    "last24hPoints": "03cef47d5200",
    "points": "03cef47d5200",
    "positions": 1
  },
  {
    "address": "G22LyUUAAZ5oyEeHuCWsrRvGnpn5fTwd7N9A2dMDNCZd",
    "rank": 38,
    "last24hPoints": "03c70fe45f00",
    "points": "03c70fe45f00",
    "positions": 1
  },
  {
    "address": "825EpEVg26X2qdEwVcgeJe7mA5MnYD4jpBLTXAj4mSza",
    "rank": 39,
    "last24hPoints": "03c4afecb900",
    "points": "03c4afecb900",
    "positions": 1
  },
  {
    "address": "BKoLETt9ZSP5fuehVM6B25j65Sa8ut881Z3E5HBaqJnt",
    "rank": 40,
    "last24hPoints": "03bffbe92f00",
    "points": "03bffbe92f00",
    "positions": 1
  },
  {
    "address": "GKrQqP1ghqrQ7S4UaXs6xqaCK19CpS9DUtzZWDyhrcVM",
    "rank": 41,
    "last24hPoints": "03bb005f1900",
    "points": "03bb005f1900",
    "positions": 2
  },
  {
    "address": "Ev5kKoAsh4XzXrJp4Kbj7MFzj2pBZB6Y8v7tjKX3GJnz",
    "rank": 42,
    "last24hPoints": "03b8888fef00",
    "points": "03b8888fef00",
    "positions": 1
  },
  {
    "address": "6z8kWL7KUeAtCZjJfBb9KhLjaytRdVH5PgoDZRuq4kv2",
    "rank": 43,
    "last24hPoints": "034e6eb9c200",
    "points": "034e6eb9c200",
    "positions": 1
  },
  {
    "address": "296qbMwRi3KFpJg1qKh1zpFozQGREkGmQ2RrnckX5vMw",
    "rank": 44,
    "last24hPoints": "03204f0ba500",
    "points": "03204f0ba500",
    "positions": 2
  },
  {
    "address": "31ykqjfXzfHLggBamDEgKJAnK3xyY2C5m74kRZ4ERj5J",
    "rank": 45,
    "last24hPoints": "02ccc4e62100",
    "points": "02ccc4e62100",
    "positions": 0
  },
  {
    "address": "ejDsbS4B8pswMqxP3YgF8Bq3jZp1tbPjRU8VLrEKa8n",
    "rank": 46,
    "last24hPoints": "02ba9bbc9500",
    "points": "02ba9bbc9500",
    "positions": 1
  },
  {
    "address": "4DYpCGAEHHMSQoyCjaNbmnJ2z5nwajfkAmzhiH15SX3r",
    "rank": 47,
    "last24hPoints": "025d97ae5a00",
    "points": "025d97ae5a00",
    "positions": 1
  },
  {
    "address": "EcGWqXGFTaJ1doa7YPem5NFzaXxiSpLXt314aYoyovku",
    "rank": 48,
    "last24hPoints": "0257d7724300",
    "points": "0257d7724300",
    "positions": 1
  },
  {
    "address": "siCRpbTXfkvnmq7zqSUaPoQXPg5nYuALb2CF3qehqSn",
    "rank": 49,
    "last24hPoints": "024a506a9e00",
    "points": "024a506a9e00",
    "positions": 0
  },
  {
    "address": "EWDvKbRS9M3i4zSA6UYG7E8R3KV6k6JKunUi9UuMniuc",
    "rank": 50,
    "last24hPoints": "02371b088500",
    "points": "02371b088500",
    "positions": 1
  },
  {
    "address": "CQL3JxyV6kS9TqFVKPDvHF4EMn2uWCZr3ipgv8KLiYiQ",
    "rank": 51,
    "last24hPoints": "022ab21b1000",
    "points": "022ab21b1000",
    "positions": 1
  },
  {
    "address": "EW2HhcsGiXUbxB1Vg7Ycg56NeKXkkKRo4hgU2sEpom97",
    "rank": 52,
    "last24hPoints": "02282e602400",
    "points": "02282e602400",
    "positions": 1
  },
  {
    "address": "4rfHwgFcS1KimwfxHcR2mAx4KAac84YfAiBz269UG3cQ",
    "rank": 53,
    "last24hPoints": "022474b38400",
    "points": "022474b38400",
    "positions": 1
  },
  {
    "address": "FzTFM59ZeiKv1pr3errd2gHidAYMfo6hkGh2jpt2kXBE",
    "rank": 54,
    "last24hPoints": "0221a9720c00",
    "points": "0221a9720c00",
    "positions": 1
  },
  {
    "address": "EtxtgjMf66ydeKv3vBooqKHWnp6YnjHusWLNsFaDcfD7",
    "rank": 55,
    "last24hPoints": "02120fef2e00",
    "points": "02120fef2e00",
    "positions": 1
  },
  {
    "address": "CyHbg5Vq6sAJkbodvpnmZhDM4AtnyYcuPvaNVRYhAhYC",
    "rank": 56,
    "last24hPoints": "01d326c26000",
    "points": "01d326c26000",
    "positions": 1
  },
  {
    "address": "C63WkxS9t1r8o91CNrKniDuBVocTSjFzS3brxzKLCipQ",
    "rank": 57,
    "last24hPoints": "01b7008ec700",
    "points": "01b7008ec700",
    "positions": 2
  },
  {
    "address": "8Xj7CuzmsFiJxUVAtS3brkafhmMX2AQ2hSf1RNa9iGYd",
    "rank": 58,
    "last24hPoints": "01b5595d6000",
    "points": "01b5595d6000",
    "positions": 1
  },
  {
    "address": "2qhqhQyHa1ZzN3KYRc65gpiffzdLyC6u5iDcDBmwh56t",
    "rank": 59,
    "last24hPoints": "01a9eac6d500",
    "points": "01a9eac6d500",
    "positions": 1
  },
  {
    "address": "9qT3pBW3F9Rs4dYoBF8boJTfgiCJuWHuz4TwzeWCUjW3",
    "rank": 60,
    "last24hPoints": "01a1417be100",
    "points": "01a1417be100",
    "positions": 2
  },
  {
    "address": "68cZySyPjipap2TBkTF6xke13wfo85KWM6C56FQ9JsXC",
    "rank": 61,
    "last24hPoints": "018f361fba00",
    "points": "018f361fba00",
    "positions": 1
  },
  {
    "address": "7EQ9jBGEvH8eZHJFrt1XYE5pRV2uWwYzdV8cTaL77uvx",
    "rank": 62,
    "last24hPoints": "018b46ce3100",
    "points": "018b46ce3100",
    "positions": 1
  },
  {
    "address": "CUBW8bNn8DJ7UvncMcWexSD6hM5PycaYzpZz29nkeZnV",
    "rank": 63,
    "last24hPoints": "01586d26a900",
    "points": "01586d26a900",
    "positions": 2
  },
  {
    "address": "3d2Fi3eTFZG3z2u1nvsbHv5naCMojsu6kJeVL6Tu3sud",
    "rank": 64,
    "last24hPoints": "015347e36c00",
    "points": "015347e36c00",
    "positions": 1
  },
  {
    "address": "7KQETrPtGTwZfkG8Tqsgtiko4Dmky6p4mP6HLZ9WRmPc",
    "rank": 65,
    "last24hPoints": "014f17013800",
    "points": "014f17013800",
    "positions": 2
  },
  {
    "address": "G2s2wqs4gqKyt3htBpP3DdRaUFSJZF3WqNCv9JiiVq7w",
    "rank": 66,
    "last24hPoints": "0130de526600",
    "points": "0130de526600",
    "positions": 1
  },
  {
    "address": "8nfFXni5WaAyYN4MMm2fDg8ANreicoCBByfBhh9MA8d1",
    "rank": 67,
    "last24hPoints": "011ef0c3a400",
    "points": "011ef0c3a400",
    "positions": 3
  },
  {
    "address": "EoZJFXNeZMfnYdcv66XhiKWaKZECisKbD4GgL7WyUZt",
    "rank": 68,
    "last24hPoints": "eab17b6000",
    "points": "eab17b6000",
    "positions": 1
  },
  {
    "address": "2GohJmd5tgXETvsVQV4mWixG1LNBZya9BrJ1cM4g8En9",
    "rank": 69,
    "last24hPoints": "df48dab600",
    "points": "df48dab600",
    "positions": 1
  },
  {
    "address": "bD5LhCwB4dGByDh5smBX8iqCuVdYxkbGnm9QhhdyMpa",
    "rank": 70,
    "last24hPoints": "de3ca22900",
    "points": "de3ca22900",
    "positions": 1
  },
  {
    "address": "GZTbayrxCDAjVmWAvczpAzMmuW5VoXGaUPSUNchSb1rJ",
    "rank": 71,
    "last24hPoints": "d062283600",
    "points": "d062283600",
    "positions": 1
  },
  {
    "address": "4y5JGxWxde1JWMTeQhScgZybnHxGVe8ewsuEVUbw6iP8",
    "rank": 72,
    "last24hPoints": "bf03a68c00",
    "points": "bf03a68c00",
    "positions": 2
  },
  {
    "address": "7P5veEKHS1MLW3n8TfjJ52Yxuxgz7vQsZrReQRaiUqDo",
    "rank": 73,
    "last24hPoints": "bbb543be00",
    "points": "bbb543be00",
    "positions": 1
  },
  {
    "address": "9uuWWiifNFCW8Tt8nHWNBypRqvZSVWgsHCUrTywLPCyD",
    "rank": 74,
    "last24hPoints": "a7eadeac00",
    "points": "a7eadeac00",
    "positions": 1
  },
  {
    "address": "6nNYC4r5dDEvGwASmvauDWrGAm1pMRLRsg7iGYLUMznJ",
    "rank": 75,
    "last24hPoints": "a7380e4e00",
    "points": "a7380e4e00",
    "positions": 1
  },
  {
    "address": "AAwcymjnQEsKvDHViKNAqkTJmBbKX6jvRXvv4RRBp1AF",
    "rank": 76,
    "last24hPoints": "97c24eb600",
    "points": "97c24eb600",
    "positions": 1
  },
  {
    "address": "BV7hksJBzmNU7tauoMzboTF3NcYCoxnjY3f4BwCF6MdU",
    "rank": 77,
    "last24hPoints": "95eb6e4700",
    "points": "95eb6e4700",
    "positions": 1
  },
  {
    "address": "7ayp3FVZ14yuWcmUtxp7bCL6Rga5aTFcK3P5PjYpuhgo",
    "rank": 78,
    "last24hPoints": "8994627500",
    "points": "8994627500",
    "positions": 1
  },
  {
    "address": "HptKKasYS1LNDeWkHzcANaS1YZwhFu6QW87uShP1C1hv",
    "rank": 79,
    "last24hPoints": "885284ff00",
    "points": "885284ff00",
    "positions": 1
  },
  {
    "address": "7VhE5QeNhwPTxjaokwxqNaw8FaZJEnsThDufvTr4r2pn",
    "rank": 80,
    "last24hPoints": "79fadf9700",
    "points": "79fadf9700",
    "positions": 1
  },
  {
    "address": "B3nkaPVsVtQmafgshqeQoFi2ZXGyBs7QeXywadGL61gZ",
    "rank": 81,
    "last24hPoints": "7358241a00",
    "points": "7358241a00",
    "positions": 1
  },
  {
    "address": "Hz5ZXZoaWw7PCK7wP4kuTpNtTnRVBWyDut1gv1KNzwgN",
    "rank": 82,
    "last24hPoints": "7228284700",
    "points": "7228284700",
    "positions": 1
  },
  {
    "address": "BH9TgXm2Zm2xe1jgTDyjXJSi1WMb1wLDnpoaDgwEm8Fa",
    "rank": 83,
    "last24hPoints": "718143ab00",
    "points": "718143ab00",
    "positions": 1
  },
  {
    "address": "8i3UpU7CV6C8CTWFUrt67v29x7eiKH89mhvf2LsxEAQ8",
    "rank": 84,
    "last24hPoints": "6e32e0dd00",
    "points": "6e32e0dd00",
    "positions": 1
  },
  {
    "address": "bwdLVw8rwgcP4Cptcfc32e69sFM2VBrFguCnUwPidzJ",
    "rank": 85,
    "last24hPoints": "6a910bc100",
    "points": "6a910bc100",
    "positions": 1
  },
  {
    "address": "4WTYH5KRqMmjGasAVcNGTYGeLKivudPP5GgdBYPQMyrJ",
    "rank": 86,
    "last24hPoints": "694f2e4b00",
    "points": "694f2e4b00",
    "positions": 1
  },
  {
    "address": "6x9wYVgUQAPin6fJVYmKeNMKpK1QFQWmhzBQKCsxha4d",
    "rank": 87,
    "last24hPoints": "6565d2a300",
    "points": "6565d2a300",
    "positions": 1
  },
  {
    "address": "7aDtbQHJx82t9aoHQZdXcG1womHQkgKE8txM53TmttAt",
    "rank": 88,
    "last24hPoints": "61e7c0cd00",
    "points": "61e7c0cd00",
    "positions": 1
  },
  {
    "address": "WriKfXe83L2A6qpvEqiPRKqVN7dC1gLbgkZ1UFSJS81",
    "rank": 89,
    "last24hPoints": "59564d5d00",
    "points": "59564d5d00",
    "positions": 1
  },
  {
    "address": "2J4KB6gAPZqbkyWoQimTaWysnMcuVsCwACw9JvcQN2C7",
    "rank": 90,
    "last24hPoints": "557ed35800",
    "points": "557ed35800",
    "positions": 1
  },
  {
    "address": "8pYXVVMtUA9cnXezoJy6ttJBzy9Qt8keDx1diY4DngcW",
    "rank": 91,
    "last24hPoints": "4ad4eece00",
    "points": "4ad4eece00",
    "positions": 1
  },
  {
    "address": "FfR89tUzp2TBTuH87jG2JCnnhwbgjK1hi4qm2jQdq4f3",
    "rank": 92,
    "last24hPoints": "49fe5b2a00",
    "points": "49fe5b2a00",
    "positions": 1
  },
  {
    "address": "JBsWQYeAsoFQcZFyJBQLPz1AwC5pAR6AZ8rhpqdKgC3G",
    "rank": 93,
    "last24hPoints": "4744fb5500",
    "points": "4744fb5500",
    "positions": 1
  },
  {
    "address": "4ZJgWhAsQKpWXuhxATMmErPAhX7S9qJRrXyNZ7pPvCzo",
    "rank": 94,
    "last24hPoints": "45f7321d00",
    "points": "45f7321d00",
    "positions": 1
  },
  {
    "address": "13KXyaZ2JDD7KJH5UrY4BRb7NPDJPUcLbr3dwN4tF8zu",
    "rank": 95,
    "last24hPoints": "45d964b800",
    "points": "45d964b800",
    "positions": 1
  },
  {
    "address": "3nbacqq87ggfCc6FJgc3hcXarJpBjjiZXDKqaU2xAuiY",
    "rank": 96,
    "last24hPoints": "45bb975300",
    "points": "45bb975300",
    "positions": 1
  },
  {
    "address": "4ntSLU5yGByt4a8USt181T6gkWWyGWiRcnwf1eUuCmQc",
    "rank": 97,
    "last24hPoints": "4568250500",
    "points": "4568250500",
    "positions": 1
  },
  {
    "address": "3AS8vYc7CfHzZLTmsNSZsyEfyJvQs2nybPyGvscVoJEt",
    "rank": 98,
    "last24hPoints": "44af5ec600",
    "points": "44af5ec600",
    "positions": 1
  },
  {
    "address": "4aZPrrdS5bknRVvv9qznjP64buY3j7tGYtUThWcVyTwE",
    "rank": 99,
    "last24hPoints": "447fafbe00",
    "points": "447fafbe00",
    "positions": 1
  },
  {
    "address": "5gNNnw1DLJdQ62x7mbf3XmMmmwbpBdtau3dZwrVaCTPz",
    "rank": 100,
    "last24hPoints": "4432335100",
    "points": "4432335100",
    "positions": 1
  },
  {
    "address": "C45xu7SfkR1y2p9t4ZpE9bNrqSnnHCg1Ep6NCdCXEzqH",
    "rank": 101,
    "last24hPoints": "3fd797f600",
    "points": "3fd797f600",
    "positions": 1
  },
  {
    "address": "ELwrRgkMU7eWpwTEdeT1g11teBhb5sWfvt9Ryg5rX5m8",
    "rank": 102,
    "last24hPoints": "3fd797f600",
    "points": "3fd797f600",
    "positions": 1
  },
  {
    "address": "81hWk4guUshW9deF5ZaurZPeMQ5rg5dzAv25bCuG1AXQ",
    "rank": 103,
    "last24hPoints": "3fa7e8ee00",
    "points": "3fa7e8ee00",
    "positions": 1
  },
  {
    "address": "5erEoCUGjn22xajw95Qhp4RHv1H5g6k9gKby2y5xgRQb",
    "rank": 104,
    "last24hPoints": "3c29d71800",
    "points": "3c29d71800",
    "positions": 1
  },
  {
    "address": "HH3L5EZPaVd9zVHpHf4KpoqkxvD89BAUDiohVrBE8Ha2",
    "rank": 105,
    "last24hPoints": "3c001df100",
    "points": "3c001df100",
    "positions": 2
  },
  {
    "address": "3YvMaurdkmc19ncGQjVPXQmiC5HuBvdEXsgbXcCHogAr",
    "rank": 106,
    "last24hPoints": "399a306a00",
    "points": "399a306a00",
    "positions": 1
  },
  {
    "address": "wGYfNsM8GoMha8g22W2EBYTcrpzxCyQM3f7Egsj2wqC",
    "rank": 107,
    "last24hPoints": "39589fbf00",
    "points": "39589fbf00",
    "positions": 1
  },
  {
    "address": "2H64xRASm4z7TDbMPdKdCMytMNxo662ibsqGpxR5JDsN",
    "rank": 108,
    "last24hPoints": "3722614000",
    "points": "3722614000",
    "positions": 1
  },
  {
    "address": "7LEdEmpQheYZiBtBT5DGj8m3RfJEC3tVZ1GrnJEQsxro",
    "rank": 109,
    "last24hPoints": "337a964300",
    "points": "337a964300",
    "positions": 2
  },
  {
    "address": "6PrmgSUaPzztsWUsf2mrb9aBWHEmrb929YXdxebCzkBZ",
    "rank": 110,
    "last24hPoints": "3185e86f00",
    "points": "3185e86f00",
    "positions": 1
  },
  {
    "address": "EGC8FvXyL74b8HeEFbsDNMqJUpMPzG2j9e3wuxBZpDYH",
    "rank": 111,
    "last24hPoints": "30027a4e00",
    "points": "30027a4e00",
    "positions": 1
  },
  {
    "address": "J41UK3v8QX73GEu7QbvoWaJPhb18QjoLJJUTrgNWvoEM",
    "rank": 112,
    "last24hPoints": "2fa9121f00",
    "points": "2fa9121f00",
    "positions": 2
  },
  {
    "address": "EusQ25ZBa8gYwBbqQSjMQbrsnbpcrXn1KCbYkjhhhs5E",
    "rank": 113,
    "last24hPoints": "2f736d3600",
    "points": "2f736d3600",
    "positions": 2
  },
  {
    "address": "87nWs6wzE1P9SBcyMxBP37z4hvU3UtDkQDhDbtUfXDbw",
    "rank": 114,
    "last24hPoints": "2c9c3ffc00",
    "points": "2c9c3ffc00",
    "positions": 1
  },
  {
    "address": "BAJ6dxZM34FPVho8GShu1KLhzr32JZyHUYrBHWKaBWcW",
    "rank": 115,
    "last24hPoints": "2c01472200",
    "points": "2c01472200",
    "positions": 1
  },
  {
    "address": "DwnQnCiSmGmKJP6VqowLaSgcvzV5y7nh4sq6pB7LPkAN",
    "rank": 116,
    "last24hPoints": "2b428b0200",
    "points": "2b428b0200",
    "positions": 1
  },
  {
    "address": "735WWiE8mp84Cv4Xh8PdQLXAPLPkG4m8WobwAvRym66E",
    "rank": 117,
    "last24hPoints": "29d0fe8400",
    "points": "29d0fe8400",
    "positions": 1
  },
  {
    "address": "85vn9a7C3TjFr3z5hyTBNSigvMwZhGMGJBG2tQ8i9tiA",
    "rank": 118,
    "last24hPoints": "27be834b00",
    "points": "27be834b00",
    "positions": 1
  },
  {
    "address": "FwVFYLcGZgsxBBuN2zRtQJReKGfW1S6MtzMQHMXQqBSS",
    "rank": 119,
    "last24hPoints": "272f763300",
    "points": "272f763300",
    "positions": 1
  },
  {
    "address": "HRFN3Ub119oX9wq6oMAtn67XxqytUhn6v9wXN4wEbfAq",
    "rank": 120,
    "last24hPoints": "25d5c13900",
    "points": "25d5c13900",
    "positions": 1
  },
  {
    "address": "XEG6FgLmLz73CbC96wtRcYZUj89Z7kaVf6neXWq9eQZ",
    "rank": 121,
    "last24hPoints": "2522f0db00",
    "points": "2522f0db00",
    "positions": 1
  },
  {
    "address": "9nRLRtpn2X2DfeE3ARYzKR8kWRfcsZQ5Zg8612AYM67c",
    "rank": 122,
    "last24hPoints": "22bd035400",
    "points": "22bd035400",
    "positions": 1
  },
  {
    "address": "2AnN3j4V4KSQdLbW634K5hqQ1jBxSCDkzyRFunsDx7H4",
    "rank": 123,
    "last24hPoints": "228d544c00",
    "points": "228d544c00",
    "positions": 1
  },
  {
    "address": "9i2uH8bKt4oxNH8vFVTSqSpF7u7WBhCMhmW16pq6Rc4c",
    "rank": 124,
    "last24hPoints": "21f25b7200",
    "points": "21f25b7200",
    "positions": 1
  },
  {
    "address": "9Z289EtPox7zk3b7BuQ7jgqsSQQiwtxy9t8gkVqECofg",
    "rank": 125,
    "last24hPoints": "2015852200",
    "points": "2015852200",
    "positions": 1
  },
  {
    "address": "GqbQHzFbxKGZ7sYY6DyMs88ABDS3Mo7qe5GRGTpBSCcJ",
    "rank": 126,
    "last24hPoints": "1fbc1cf300",
    "points": "1fbc1cf300",
    "positions": 1
  },
  {
    "address": "3k8GsQRVKNit3byzD1PNuMHthxGj9LZKM4BEP65mPDDk",
    "rank": 127,
    "last24hPoints": "1f3ef17e00",
    "points": "1f3ef17e00",
    "positions": 2
  },
  {
    "address": "AkTeCENMjYw81ponhakQE83EoiJKzHmdije46HwSEEDG",
    "rank": 128,
    "last24hPoints": "1edf936e00",
    "points": "1edf936e00",
    "positions": 1
  },
  {
    "address": "Bru9f3Yfvp7TMiiJNjQW7Mj27Z7vZUnVKsczKyz7EF4p",
    "rank": 129,
    "last24hPoints": "1e862b3f00",
    "points": "1e862b3f00",
    "positions": 1
  },
  {
    "address": "HmHFrfMYS9irC6Zk1ZmsPMJvzC85kLLdfgMypE8USZj4",
    "rank": 130,
    "last24hPoints": "1d149ec100",
    "points": "1d149ec100",
    "positions": 1
  },
  {
    "address": "EwALY5WXaUBWdCCX14pcEgBaLYPNJarV52u7am1NxXFT",
    "rank": 131,
    "last24hPoints": "1c1451f600",
    "points": "1c1451f600",
    "positions": 3
  },
  {
    "address": "9Hv7QQrnbUoAVVv6tfbJ7VRnMbR9QKVgnTQkVG9NAdu8",
    "rank": 132,
    "last24hPoints": "1a0dc27f00",
    "points": "1a0dc27f00",
    "positions": 1
  },
  {
    "address": "295P1NUzg7rih9wLZK5359CHVyNc6wiQpHdZuWn8XUXB",
    "rank": 133,
    "last24hPoints": "19de137700",
    "points": "19de137700",
    "positions": 1
  },
  {
    "address": "6aw4feweTvmBU4GN7j8ZEz1rYjxRfByUEnakaQVYbWen",
    "rank": 134,
    "last24hPoints": "18131eca00",
    "points": "18131eca00",
    "positions": 1
  },
  {
    "address": "DhquiQMJcTq4SJf5pAYipZs5axKWjBhKPgFgREvNJ4j6",
    "rank": 135,
    "last24hPoints": "17f5516500",
    "points": "17f5516500",
    "positions": 1
  },
  {
    "address": "GPSngmevfhbRG2NzCKubaoNxJ38z3XEGPJjbxeBWTsNX",
    "rank": 136,
    "last24hPoints": "17bfac7c00",
    "points": "17bfac7c00",
    "positions": 1
  },
  {
    "address": "85f9W2uJ9xaxE515jFXfFcZqtdXkVKCENHcqpeDbiAmN",
    "rank": 137,
    "last24hPoints": "164e1ffe00",
    "points": "164e1ffe00",
    "positions": 1
  },
  {
    "address": "FJbqbDoX6VbVABEJDijVAEy2nHi94RX9FGwGHk51AEqE",
    "rank": 138,
    "last24hPoints": "14c4bbfc00",
    "points": "14c4bbfc00",
    "positions": 1
  },
  {
    "address": "12DTBJ8PRaz5LJX5iAEeBWqH8Ds2SZiMepvg8EqoSdja",
    "rank": 139,
    "last24hPoints": "147d357000",
    "points": "147d357000",
    "positions": 2
  },
  {
    "address": "4MiZHFA3vpk12jc93mktPn3Pe9VxrzwSFF7EqdcktSoJ",
    "rank": 140,
    "last24hPoints": "142fb90300",
    "points": "142fb90300",
    "positions": 1
  },
  {
    "address": "5wv22ed541FWJskxxEwqUe1iL8V87nyU7ifdoRVkwnDC",
    "rank": 141,
    "last24hPoints": "141dd76000",
    "points": "141dd76000",
    "positions": 1
  },
  {
    "address": "8YBCwLQ35CSf8GkM2z9eD5idcTA9ZhFnoAz2wC1ZvY8z",
    "rank": 142,
    "last24hPoints": "1411eb9e00",
    "points": "1411eb9e00",
    "positions": 1
  },
  {
    "address": "7hJNbRsGV38zXSavSPXcKM7mWXDpk6sZCZYNpKAZ9YBo",
    "rank": 143,
    "last24hPoints": "135f1b4000",
    "points": "135f1b4000",
    "positions": 1
  },
  {
    "address": "8QU9c8SYWdR5SJm6EraLquLoU6DrkNgvX6JRL8we4nhh",
    "rank": 144,
    "last24hPoints": "134d399d00",
    "points": "134d399d00",
    "positions": 1
  },
  {
    "address": "2rNsprmghvETLhbKg6JojrmdfqvkkBTDwFjEjq93WGGP",
    "rank": 145,
    "last24hPoints": "13414ddb00",
    "points": "13414ddb00",
    "positions": 1
  },
  {
    "address": "GhRna8VYkq5DWuYFxREieHhKwzTRw53tJcVCFbLNWrJu",
    "rank": 146,
    "last24hPoints": "12dbf9ea00",
    "points": "12dbf9ea00",
    "positions": 1
  },
  {
    "address": "6B6AysTt13iRxW2XBs6sTtdbR9raSHbSxDgVJHWURvSH",
    "rank": 147,
    "last24hPoints": "12b836a400",
    "points": "12b836a400",
    "positions": 1
  },
  {
    "address": "D3bVaFb23qxjAiPiyQJGCDE3eFma1ayc9y2sxY1H35Es",
    "rank": 148,
    "last24hPoints": "128291bb00",
    "points": "128291bb00",
    "positions": 1
  },
  {
    "address": "Ds2XgQSoyT1iDV6tVUsi9iHzbYeXRcZpjhsT8fjdpZ66",
    "rank": 149,
    "last24hPoints": "127c9bda00",
    "points": "127c9bda00",
    "positions": 1
  },
  {
    "address": "75pJGQw59NrzCP6RcQChgzcQ2G1SsLTHhbhrPJ8w193J",
    "rank": 150,
    "last24hPoints": "1276a5f900",
    "points": "1276a5f900",
    "positions": 1
  },
  {
    "address": "1FtdUwTfMMFhJ2CHWoTspPd2krp5QnPWBSkxgrqadXC",
    "rank": 151,
    "last24hPoints": "125ece7500",
    "points": "125ece7500",
    "positions": 1
  },
  {
    "address": "C14VrCu3YuoW8An2JHSxowCPnzVtCRYiVkv5g3aVuSSM",
    "rank": 152,
    "last24hPoints": "11ed8ec200",
    "points": "11ed8ec200",
    "positions": 1
  },
  {
    "address": "BSRWGz4xfGQuiFdQfEGnZaP3KhcJ5Eomrwo4Hf9abpwP",
    "rank": 153,
    "last24hPoints": "11c3d59b00",
    "points": "11c3d59b00",
    "positions": 2
  },
  {
    "address": "6msG9465ieviaCK8Gas9npxcxUo7D9mjthT8KMye5XuQ",
    "rank": 154,
    "last24hPoints": "118244f000",
    "points": "118244f000",
    "positions": 1
  },
  {
    "address": "EoNLfVWWZoGqX5JKmishUgvdJbod9ttidZhKmvHaJ1Ph",
    "rank": 155,
    "last24hPoints": "115e81aa00",
    "points": "115e81aa00",
    "positions": 1
  },
  {
    "address": "6GG2n23FYeZWEzqEQZFBvoB73JvV3oKaBCT11tiwqzpu",
    "rank": 156,
    "last24hPoints": "1099cfa900",
    "points": "1099cfa900",
    "positions": 1
  },
  {
    "address": "875tuunGaMRLiauyBiV6jcn6weCJeToa11HQ1pNnUcRH",
    "rank": 157,
    "last24hPoints": "107c024400",
    "points": "107c024400",
    "positions": 1
  },
  {
    "address": "DfVw1akQ8AvZH9rv9TYmk5zCUhdjzkMH2Ui2e2stqyFi",
    "rank": 158,
    "last24hPoints": "10642ac000",
    "points": "10642ac000",
    "positions": 1
  },
  {
    "address": "AiSNcES95rKtZQU4poG1bLb2BiHfu8zugZtgDtUcqqWS",
    "rank": 159,
    "last24hPoints": "0f2e390c00",
    "points": "0f2e390c00",
    "positions": 1
  },
  {
    "address": "483NhH5H4t8XL5m9pu3Z3zh9Qa8fvBo8tGvUYniEyAdY",
    "rank": 160,
    "last24hPoints": "0f1c576900",
    "points": "0f1c576900",
    "positions": 1
  },
  {
    "address": "DaCnxmE8ygbWprukoEixko3HF65VDQ9tDiPo38cc1uh3",
    "rank": 161,
    "last24hPoints": "0e4bb9a600",
    "points": "0e4bb9a600",
    "positions": 2
  },
  {
    "address": "2E3U21sTvAmfkcc7TYMABonE7xsmNKaShX1HJg7xVow8",
    "rank": 162,
    "last24hPoints": "0dfe3d3900",
    "points": "0dfe3d3900",
    "positions": 1
  },
  {
    "address": "2b9LePhdQFRjy6RmPvpK2AookHvaaB5w9Z49Dm1WeLBN",
    "rank": 163,
    "last24hPoints": "0cf7fa8d00",
    "points": "0cf7fa8d00",
    "positions": 1
  },
  {
    "address": "AGGWT3b1iki5u37kkxBsT8dR16RLyYikWXmKV3rhPJND",
    "rank": 164,
    "last24hPoints": "0cd4374700",
    "points": "0cd4374700",
    "positions": 1
  },
  {
    "address": "3qSTECLuKXC7GjqMRdjz5fHMDewkXF8qW8ha8GUZXQKs",
    "rank": 165,
    "last24hPoints": "0bd3ea7c00",
    "points": "0bd3ea7c00",
    "positions": 1
  },
  {
    "address": "HJCZe7RSQrB3XWndnNnNNzWScFqF1LcNZwTVcfHzmdQf",
    "rank": 166,
    "last24hPoints": "0b68a0aa00",
    "points": "0b68a0aa00",
    "positions": 1
  },
  {
    "address": "CXGHyhhfPUNeohuakzdFXRVbzwJ46DXYVnj5Dqu38Qnp",
    "rank": 167,
    "last24hPoints": "0b62aac900",
    "points": "0b62aac900",
    "positions": 1
  },
  {
    "address": "2UuLxPm1Hgi6QGEq6aqANqU4bPHgWLYM7ci8m6ZoYXbd",
    "rank": 168,
    "last24hPoints": "0b38f1a200",
    "points": "0b38f1a200",
    "positions": 1
  },
  {
    "address": "4rDWaubpSqQc5JVKVgttmEywtLbE22fvmG7K4xLP18AN",
    "rank": 169,
    "last24hPoints": "0b38f1a200",
    "points": "0b38f1a200",
    "positions": 1
  },
  {
    "address": "9iRfyBGDdQzF1qm6HbQumbTg4nFLi3ceetcyzj19Ku2i",
    "rank": 170,
    "last24hPoints": "0b2d05e000",
    "points": "0b2d05e000",
    "positions": 1
  },
  {
    "address": "5WVxzCyP9TVNqJNMfFCZqAvoAKxsDriuSyL4EPMRAf8V",
    "rank": 171,
    "last24hPoints": "0afd56d800",
    "points": "0afd56d800",
    "positions": 1
  },
  {
    "address": "Ez6gQcmyJC38sqBg2id9WKRVAfpapuLEVFEAR38sEgWr",
    "rank": 172,
    "last24hPoints": "0adf897300",
    "points": "0adf897300",
    "positions": 1
  },
  {
    "address": "8byYFz8rBD2uGuuE4vof8RoqY4TEGKwMnnnqtoUF2oa9",
    "rank": 173,
    "last24hPoints": "0abbc62d00",
    "points": "0abbc62d00",
    "positions": 1
  },
  {
    "address": "GL2NkNXobJjQHtUbdr1Fprhpd9ZHZeqR5ZsXsBLGBq1c",
    "rank": 174,
    "last24hPoints": "0a38a4d700",
    "points": "0a38a4d700",
    "positions": 1
  },
  {
    "address": "9PY2KHy8xpn6SpGVL8snGjgQESXy7EbyhSi4rCTzivqG",
    "rank": 175,
    "last24hPoints": "0a1ad77200",
    "points": "0a1ad77200",
    "positions": 0
  },
  {
    "address": "2VSic9LFDrfF3STk6szVwhSvvVRmgmBNEc6hZ3AZax1R",
    "rank": 176,
    "last24hPoints": "09eb286a00",
    "points": "09eb286a00",
    "positions": 1
  },
  {
    "address": "F8k8qYVTn5zabvAa5LQwH4pshuB9cehUagN4BCLAppLj",
    "rank": 177,
    "last24hPoints": "09d946c700",
    "points": "09d946c700",
    "positions": 1
  },
  {
    "address": "7cuN1DDYLLJmrqQS3VfbdJWh6bYSWpPAoTnkFEKmdfJW",
    "rank": 178,
    "last24hPoints": "09b5838100",
    "points": "09b5838100",
    "positions": 1
  },
  {
    "address": "Bn56d1yRKGznim38wRtJtfYUPGKvkhXhvBJnXPMtm6K4",
    "rank": 179,
    "last24hPoints": "09a3a1de00",
    "points": "09a3a1de00",
    "positions": 1
  },
  {
    "address": "7MGnr8TXdC7uQ8T2jrzidsVQkzmWcmkP6Gk7HMny1u3U",
    "rank": 180,
    "last24hPoints": "0997b61c00",
    "points": "0997b61c00",
    "positions": 1
  },
  {
    "address": "FCizqiBQFk244d3yK6PG4z76QaN3UtgENx9uwA9zkUUn",
    "rank": 181,
    "last24hPoints": "0968071400",
    "points": "0968071400",
    "positions": 1
  },
  {
    "address": "DoWefagGh1bVH8NgjdRpHriAqVRauajP3eKXbLoqk8kZ",
    "rank": 182,
    "last24hPoints": "091a8aa700",
    "points": "091a8aa700",
    "positions": 1
  },
  {
    "address": "EGc5G5SfBzNBGdhvF21pjByVAq41961vNkX3L4S4KGzo",
    "rank": 183,
    "last24hPoints": "08deefdd00",
    "points": "08deefdd00",
    "positions": 1
  },
  {
    "address": "AqEo13a3dCYTopDnuGfbMioQe2nq6U1HPr5yz1fxgYwj",
    "rank": 184,
    "last24hPoints": "089d5f3200",
    "points": "089d5f3200",
    "positions": 1
  },
  {
    "address": "MPm2sZY1WzRgZMDWbPizhSXC3frB2gW8v5BHykQ8hRp",
    "rank": 185,
    "last24hPoints": "085bce8700",
    "points": "085bce8700",
    "positions": 1
  },
  {
    "address": "9iEVqYCUqePDJssVuyxotzotbevXNVqzccZJmMwQkniN",
    "rank": 186,
    "last24hPoints": "082033bd00",
    "points": "082033bd00",
    "positions": 1
  },
  {
    "address": "Bm3CyZaDp1DcLnKNRtx3g6F4RBeX5ocAW8VMZj7pqBV3",
    "rank": 187,
    "last24hPoints": "081a3ddc00",
    "points": "081a3ddc00",
    "positions": 1
  },
  {
    "address": "Er4zCokfhagHZqPkNiS7AzisMN42zHmVzY8fr1PcX8pf",
    "rank": 188,
    "last24hPoints": "07badfcc00",
    "points": "07badfcc00",
    "positions": 1
  },
  {
    "address": "9xhAHa1tzs27QzWpfEYcGGResrJo16eAFSL4TduYEweo",
    "rank": 189,
    "last24hPoints": "076d635f00",
    "points": "076d635f00",
    "positions": 1
  },
  {
    "address": "JCgHbKRj7WWJxN1BBXRWwAKsc5p4FrTzP3rhavRPUNi8",
    "rank": 190,
    "last24hPoints": "07676d7e00",
    "points": "07676d7e00",
    "positions": 1
  },
  {
    "address": "H8v259zcCvDFJGz9WrHrYPkDqtBoosDBVNduGkQ7nLYy",
    "rank": 191,
    "last24hPoints": "0737be7600",
    "points": "0737be7600",
    "positions": 0
  },
  {
    "address": "JBX86p6DCaQCEyGZTY89XUyZ1KFdt4fdU21CMYgxWndq",
    "rank": 192,
    "last24hPoints": "0719f11100",
    "points": "0719f11100",
    "positions": 1
  },
  {
    "address": "AQ9mY38uQMMdz8w1epiWVXqxUnWPZQF1b9Pv2GkJrkwN",
    "rank": 193,
    "last24hPoints": "06f037ea00",
    "points": "06f037ea00",
    "positions": 2
  },
  {
    "address": "28TxhZSsaQvFouJmW5NUJWQguqDgKnZQBvzrTQBX2qRv",
    "rank": 194,
    "last24hPoints": "06de564700",
    "points": "06de564700",
    "positions": 1
  },
  {
    "address": "3jaPf3pmfDod48vCUaQ68XCfbphTpwktH1jaLjDDzAN6",
    "rank": 195,
    "last24hPoints": "06de564700",
    "points": "06de564700",
    "positions": 1
  },
  {
    "address": "HCc897idLb2MSx9hyz8RLqAWoxSsXEaw7fp6tybUoqhE",
    "rank": 196,
    "last24hPoints": "06c088e200",
    "points": "06c088e200",
    "positions": 1
  },
  {
    "address": "DYzgrZbedYhUAqVcxzoudnNhV5Yih8w191qT2AGo69cv",
    "rank": 197,
    "last24hPoints": "066d169400",
    "points": "066d169400",
    "positions": 1
  },
  {
    "address": "9tkX2E1zMEw1XB4VdH91uBCkbQpU1r5bZYq6gbKXyJVv",
    "rank": 198,
    "last24hPoints": "0649534e00",
    "points": "0649534e00",
    "positions": 0
  },
  {
    "address": "9gXUmVJRraJNP3tPsEbMUGCuBRKF3DTH9QirdXbGsz8h",
    "rank": 199,
    "last24hPoints": "062b85e900",
    "points": "062b85e900",
    "positions": 1
  },
  {
    "address": "6SD6sxch815pCj3FsG2ypmXDg7MRyRT3UDjGtogPTvBz",
    "rank": 200,
    "last24hPoints": "0607c2a300",
    "points": "0607c2a300",
    "positions": 1
  },
  {
    "address": "3sPZNqpVDDuSGrACcixYUHHWiyj6dqVH4GoWB9TXEzGL",
    "rank": 201,
    "last24hPoints": "05fbd6e100",
    "points": "05fbd6e100",
    "positions": 1
  },
  {
    "address": "4ehhVop3NATi5EpcVXS3iL9yHnjNkZJEDCFBEwXP9UWE",
    "rank": 202,
    "last24hPoints": "05fbd6e100",
    "points": "05fbd6e100",
    "positions": 1
  },
  {
    "address": "FPjE8fXpdMGHwt6PbtycHk8arrZVutg6ZLJBdWb42BAH",
    "rank": 203,
    "last24hPoints": "05f5e10000",
    "points": "05f5e10000",
    "positions": 1
  },
  {
    "address": "5wtJsYWA7rzEMGZmRqzCFc29RDewxwsLWQBbjL6zRUxP",
    "rank": 204,
    "last24hPoints": "05d8139b00",
    "points": "05d8139b00",
    "positions": 1
  },
  {
    "address": "7MMZ5n2VFRDoL4G5C3XW4oFHGVrfcqDDARXidoY86Hpy",
    "rank": 205,
    "last24hPoints": "05d8139b00",
    "points": "05d8139b00",
    "positions": 1
  },
  {
    "address": "328i1a7mgPzKwbtUwt14up1zuP5z5FRyytgVyjR37uvJ",
    "rank": 206,
    "last24hPoints": "05ae5a7400",
    "points": "05ae5a7400",
    "positions": 1
  },
  {
    "address": "EutRhaH3ZCWBzRsDpUmDNA4Rk3dVB6PgdY1J95jtQuFA",
    "rank": 207,
    "last24hPoints": "05ae5a7400",
    "points": "05ae5a7400",
    "positions": 1
  },
  {
    "address": "9c1maU5d7y3xu896WfyFRXtPmzXy6bXzu49Uk3PEJ9Kj",
    "rank": 208,
    "last24hPoints": "0578b58b00",
    "points": "0578b58b00",
    "positions": 1
  },
  {
    "address": "3tHhrQFGDoaWUHCyKFbQbqhKGk4jjGFgfWdwo2Kcn5u5",
    "rank": 209,
    "last24hPoints": "0572bfaa00",
    "points": "0572bfaa00",
    "positions": 1
  },
  {
    "address": "BuYNYL7Y9LQehPZh7iWcWXu3ViSYJs5mo2H14vjaBStr",
    "rank": 210,
    "last24hPoints": "050d6bb900",
    "points": "050d6bb900",
    "positions": 1
  },
  {
    "address": "J5cDtuMhQ6JGUoghC9cQg4uNCrMg9uFw3eUD1HyuXQGJ",
    "rank": 211,
    "last24hPoints": "04cbdb0e00",
    "points": "04cbdb0e00",
    "positions": 1
  },
  {
    "address": "C4YM7uNY7UvF4a1mb3CgDzPwFs4RogTsQyyQVfCK9f3g",
    "rank": 212,
    "last24hPoints": "0490404400",
    "points": "0490404400",
    "positions": 1
  },
  {
    "address": "9v5AzEtCoVw4Mcn9z2m2JJ3hbwvJQnoXc6eMVpZBJ67U",
    "rank": 213,
    "last24hPoints": "047868c000",
    "points": "047868c000",
    "positions": 1
  },
  {
    "address": "QHxRXASrHMtaNFwNAD3qAMGTkYekxVVBTVVbNzJqGqF",
    "rank": 214,
    "last24hPoints": "047868c000",
    "points": "047868c000",
    "positions": 1
  },
  {
    "address": "Cu9jkHB1g4eKWLACjwmrtpkVjR3amBHsMFe8sJjRxpPx",
    "rank": 215,
    "last24hPoints": "047272df00",
    "points": "047272df00",
    "positions": 1
  },
  {
    "address": "sxWNpWacJ2s3w2TK9y6gEvKaKuMJJpFvWMPJsSPjdNb",
    "rank": 216,
    "last24hPoints": "0460913c00",
    "points": "0460913c00",
    "positions": 1
  },
  {
    "address": "GLd1osgHGWj8jbU6ncPwd38viMM7VAGLFL3DTMUfwFSj",
    "rank": 217,
    "last24hPoints": "045a9b5b00",
    "points": "045a9b5b00",
    "positions": 1
  },
  {
    "address": "BGGzHSe41ZF7GaE985xBcTYygmjF1u1Za7h1sniqSN7R",
    "rank": 218,
    "last24hPoints": "03fb3d4b00",
    "points": "03fb3d4b00",
    "positions": 0
  },
  {
    "address": "93uM3DfC8oN9usMJ9tpwE1Fa7VfTdqTwinvqpQef2egP",
    "rank": 219,
    "last24hPoints": "03ef518900",
    "points": "03ef518900",
    "positions": 1
  },
  {
    "address": "BH3znc2Az9MbbRprRz2csowb2skBrbHGLdaCeREWTBL3",
    "rank": 220,
    "last24hPoints": "03ef518900",
    "points": "03ef518900",
    "positions": 1
  },
  {
    "address": "3yVvYJjh7n235ofcBqftvKQdcfCFRz7YxbcBd2QSbqw1",
    "rank": 221,
    "last24hPoints": "03dd6fe600",
    "points": "03dd6fe600",
    "positions": 0
  },
  {
    "address": "AsHMjuB1xkRFaCJPh3g2noDQSowMZuF3sDLsnbH7zJAt",
    "rank": 222,
    "last24hPoints": "03adc0de00",
    "points": "03adc0de00",
    "positions": 1
  },
  {
    "address": "4XdqB6WvK8UDNH4yEbtLfiCSoMZ7cz9WBtHQKXYXYnAs",
    "rank": 223,
    "last24hPoints": "03a7cafd00",
    "points": "03a7cafd00",
    "positions": 1
  },
  {
    "address": "CkBHx6uoUxc1rQq6iuE18xRCQ4s38bAZBgMfSKUt4Xaa",
    "rank": 224,
    "last24hPoints": "039bdf3b00",
    "points": "039bdf3b00",
    "positions": 1
  },
  {
    "address": "E1kiZEKAkjBAaQXr6WsLLja7ukNkgb26NBztJBJieavt",
    "rank": 225,
    "last24hPoints": "0395e95a00",
    "points": "0395e95a00",
    "positions": 1
  },
  {
    "address": "ChjzssqQgNJZFvafXnP5fGehpcbXKA59vALMwGPAQ21m",
    "rank": 226,
    "last24hPoints": "038407b700",
    "points": "038407b700",
    "positions": 1
  },
  {
    "address": "3h73bGVzpkMdnT6GHpdLyz4kNHZTDZgSUw7pLQb6tjU6",
    "rank": 227,
    "last24hPoints": "037e11d600",
    "points": "037e11d600",
    "positions": 1
  },
  {
    "address": "9uqztB5Jpi9tzVCrX3s3djWiTRsdkWGvhNJPxHzQmUAf",
    "rank": 228,
    "last24hPoints": "03781bf500",
    "points": "03781bf500",
    "positions": 1
  },
  {
    "address": "7UE5VyJn9eyd8QTxY7GCay9eLXV9AS927fzdkLMA34xc",
    "rank": 229,
    "last24hPoints": "0372261400",
    "points": "0372261400",
    "positions": 1
  },
  {
    "address": "54uGZHTEUhaAw5kL4B8Kn7J1WR16SQEVwrdgrw7zKjJx",
    "rank": 230,
    "last24hPoints": "03663a5200",
    "points": "03663a5200",
    "positions": 1
  },
  {
    "address": "B8Jbk2SEcJ5TT3nHP2WMgPkpE8seoWE1s6gxR7nUB3BX",
    "rank": 231,
    "last24hPoints": "03663a5200",
    "points": "03663a5200",
    "positions": 1
  },
  {
    "address": "8kZi9Pbjq6zh35ZMYYrQBStoLekA5W9csKFeWMdMBzb2",
    "rank": 232,
    "last24hPoints": "0360447100",
    "points": "0360447100",
    "positions": 1
  },
  {
    "address": "843PaMRMt9GSMmqd1LRAixcTM56WqPFQUzfdQThiHei4",
    "rank": 233,
    "last24hPoints": "035a4e9000",
    "points": "035a4e9000",
    "positions": 1
  },
  {
    "address": "CxghcnQ2wECoJyMwFjd6yNmf9gNis6SgqCnxuTmYpE82",
    "rank": 234,
    "last24hPoints": "02c54b9700",
    "points": "02c54b9700",
    "positions": 1
  },
  {
    "address": "3Uj2ZE41iaMs22FSfL1ekyUAENLMhF3aj6u898yXLRTS",
    "rank": 235,
    "last24hPoints": "02ad741300",
    "points": "02ad741300",
    "positions": 1
  },
  {
    "address": "75CwGefiyPkZt4SSrBeTYRQuALSccJKcA2vfamJtzYMb",
    "rank": 236,
    "last24hPoints": "02a77e3200",
    "points": "02a77e3200",
    "positions": 1
  },
  {
    "address": "9gRLEbtA5EoeyNFMagCeMpCS82HS9HyohkCJGSEdwP2E",
    "rank": 237,
    "last24hPoints": "0289b0cd00",
    "points": "0289b0cd00",
    "positions": 1
  },
  {
    "address": "8XrGnqkJgticWZZ6oyY6K3E3oqABoyMkQ8XZEqqdVNd4",
    "rank": 238,
    "last24hPoints": "0289b0cd00",
    "points": "0289b0cd00",
    "positions": 1
  },
  {
    "address": "yiAu1yF3CkoY7evHZryDUJs2bLQVhVChYt2KN33V3Nq",
    "rank": 239,
    "last24hPoints": "027dc50b00",
    "points": "027dc50b00",
    "positions": 1
  },
  {
    "address": "DoV4nWWpet7VqP2eZtLric6ZV29zwPQuiPf8ZpnfhHHw",
    "rank": 240,
    "last24hPoints": "026be36800",
    "points": "026be36800",
    "positions": 1
  },
  {
    "address": "7iv8AMEqXoDbw7R28oK61hnCcC2UPjzpsMHzSRZi7Kzb",
    "rank": 241,
    "last24hPoints": "0265ed8700",
    "points": "0265ed8700",
    "positions": 1
  },
  {
    "address": "5UXG262ohjVse6cXhjbVJ6qHxfE9CsfW3f7tKV2kp27U",
    "rank": 242,
    "last24hPoints": "025ff7a600",
    "points": "025ff7a600",
    "positions": 1
  },
  {
    "address": "9zeo2xoRFmF6PDeRhNR83Z9nMLumimMzao8XMBzPH6tB",
    "rank": 243,
    "last24hPoints": "024e160300",
    "points": "024e160300",
    "positions": 1
  },
  {
    "address": "5CvpcL1vQfvFo6QhpYeMJztFdavwhfS2qexfPcFsM87T",
    "rank": 244,
    "last24hPoints": "022a52bd00",
    "points": "022a52bd00",
    "positions": 1
  },
  {
    "address": "9Pd66Eaoi3g1eWvtVCKhmBCXkehPzfanAZtLLC6C7tZ7",
    "rank": 245,
    "last24hPoints": "02127b3900",
    "points": "02127b3900",
    "positions": 1
  },
  {
    "address": "AeiAMPbykXr9nLg2CGxRf8hoL3cb3jaE17JadNwsqEY6",
    "rank": 246,
    "last24hPoints": "02068f7700",
    "points": "02068f7700",
    "positions": 1
  },
  {
    "address": "EMqoGMNxSNdt698Zevv1dZXVSXku7GkAymC1sBCYh8ez",
    "rank": 247,
    "last24hPoints": "01f4add400",
    "points": "01f4add400",
    "positions": 1
  },
  {
    "address": "3u8FkZuzYAiq2jAg7dNo9ii3WPibENLWJyTiWWZzrB6P",
    "rank": 248,
    "last24hPoints": "01f4add400",
    "points": "01f4add400",
    "positions": 1
  },
  {
    "address": "DjAmQXW3yQd3xj1diifqH8ZG6QfD5FKF1ZY3y8UmJtNz",
    "rank": 249,
    "last24hPoints": "01e2cc3100",
    "points": "01e2cc3100",
    "positions": 0
  },
  {
    "address": "FsoiVpLVhdnupMRsbz8vs54ESUkbWQDoK3idmTgzCTm3",
    "rank": 250,
    "last24hPoints": "01dcd65000",
    "points": "01dcd65000",
    "positions": 0
  },
  {
    "address": "CY5i2kHJfX9bTM5uPMzo1uhoKLArC1qYKAN2ojE1H2QX",
    "rank": 251,
    "last24hPoints": "01b9130a00",
    "points": "01b9130a00",
    "positions": 1
  },
  {
    "address": "4JBjm2JTXrNtEnuyEV8xEW6DfeWw1GVEZQ8gQi1Fdzh1",
    "rank": 252,
    "last24hPoints": "01ad274800",
    "points": "01ad274800",
    "positions": 1
  },
  {
    "address": "H5Lm5hbaNTY3vzvzbxtVRdCmE7zMNvW9wNrkhRh6myNc",
    "rank": 253,
    "last24hPoints": "01a7316700",
    "points": "01a7316700",
    "positions": 1
  },
  {
    "address": "8wfh6Ym7k5EaKgPFakjKNPLgDiCQdoPEwzQCmYJzKCLX",
    "rank": 254,
    "last24hPoints": "019b45a500",
    "points": "019b45a500",
    "positions": 1
  },
  {
    "address": "FRujXNSFn6wNCp5E2k7Go2PkZRXghFkchCpNH5tdgiAX",
    "rank": 255,
    "last24hPoints": "018f59e300",
    "points": "018f59e300",
    "positions": 1
  },
  {
    "address": "79XXhAwKuVfp9kbo8HktahkPds7kY5V4E6KBox72v7i8",
    "rank": 256,
    "last24hPoints": "018f59e300",
    "points": "018f59e300",
    "positions": 1
  },
  {
    "address": "GoEkMRxxbvE6MFHGGrrmzG2NryNSVhE6FY4XM6cXyP6p",
    "rank": 257,
    "last24hPoints": "018f59e300",
    "points": "018f59e300",
    "positions": 1
  },
  {
    "address": "3rX7Vy6Ce3bWiCiaVxzzuaiJJ1mgKkCpdkFSP9SxuR4S",
    "rank": 258,
    "last24hPoints": "018f59e300",
    "points": "018f59e300",
    "positions": 1
  },
  {
    "address": "1paTB4FENxg36HnHw29UpoAE1xStWM27gKncqkeiM1L",
    "rank": 259,
    "last24hPoints": "0189640200",
    "points": "0189640200",
    "positions": 1
  },
  {
    "address": "D5NhF9z61hVyWqLE4SBRnRcEuRw9iCRR9RNuHQGCWcrP",
    "rank": 260,
    "last24hPoints": "0177825f00",
    "points": "0177825f00",
    "positions": 1
  },
  {
    "address": "4BmmHNT8JikKXhfs5G2yJ8x21mXYfipczt1aGyn7uas5",
    "rank": 261,
    "last24hPoints": "015faadb00",
    "points": "015faadb00",
    "positions": 1
  },
  {
    "address": "4W4BnLTBN1mW5BjWoyBdc97gFSVJt2meonae7FGbi1Q2",
    "rank": 262,
    "last24hPoints": "015faadb00",
    "points": "015faadb00",
    "positions": 1
  },
  {
    "address": "DhmvCZ3GbUWo4CkokfXyp8jBrKcvd9BdqJxXV3vq34TD",
    "rank": 263,
    "last24hPoints": "015faadb00",
    "points": "015faadb00",
    "positions": 1
  },
  {
    "address": "D1KESNB4vbU2kQFvRsRsqqCbtYsPQCSt9AMLG2BjHjp",
    "rank": 264,
    "last24hPoints": "0147d35700",
    "points": "0147d35700",
    "positions": 1
  },
  {
    "address": "6RzHgSoxGhrvrDDsjCRF4o2nFbpgdmfE8XBtKdrAbwm6",
    "rank": 265,
    "last24hPoints": "0147d35700",
    "points": "0147d35700",
    "positions": 1
  },
  {
    "address": "77TjjdEku2iPTZyeBNtS89RFm2EiVMD6y7WsZrti5vUV",
    "rank": 266,
    "last24hPoints": "012ffbd300",
    "points": "012ffbd300",
    "positions": 1
  },
  {
    "address": "F4m7WpvZSPn15qRqafCrkWy4GkgMkXP1b4fX4HowZVG1",
    "rank": 267,
    "last24hPoints": "012ffbd300",
    "points": "012ffbd300",
    "positions": 1
  },
  {
    "address": "42njeDcvVo87yDUCcv9KYAS45Eukw8Yt2FztpCCGBDFH",
    "rank": 268,
    "last24hPoints": "012ffbd300",
    "points": "012ffbd300",
    "positions": 1
  },
  {
    "address": "mZLQhnG3N4PydNkqMuHtjJ5aBZQkZ5RLThMtTxzdJgQ",
    "rank": 269,
    "last24hPoints": "012a05f200",
    "points": "012a05f200",
    "positions": 1
  },
  {
    "address": "4D3KPnSMk6xYZkhgsYgJ9x1bUQZzv4nwVvRuBajhQRRd",
    "rank": 270,
    "last24hPoints": "012a05f200",
    "points": "012a05f200",
    "positions": 1
  },
  {
    "address": "aXB4yVKs81u36VpkbtVKdSjtJibx1wDJQyaLPm5xVVU",
    "rank": 271,
    "last24hPoints": "0124101100",
    "points": "0124101100",
    "positions": 1
  },
  {
    "address": "BpzQDdUFewQVwFS4uFGFVNySAobvxr46Mcs6b1STHfAu",
    "rank": 272,
    "last24hPoints": "0124101100",
    "points": "0124101100",
    "positions": 1
  },
  {
    "address": "6hVFEi1fpQpzknaL875X5UbpJZCnN1ymvMjqERPbX92e",
    "rank": 273,
    "last24hPoints": "0118244f00",
    "points": "0118244f00",
    "positions": 1
  },
  {
    "address": "9VgRQmheUUjPofdoxLjNobbp9iom5UPZUYSQ2YkCx3yE",
    "rank": 274,
    "last24hPoints": "0118244f00",
    "points": "0118244f00",
    "positions": 1
  },
  {
    "address": "8Vxv8UxGfpaV9JgGkDTBb3tbaWQk6LC6tjyVAwCxwemH",
    "rank": 275,
    "last24hPoints": "010642ac00",
    "points": "010642ac00",
    "positions": 1
  },
  {
    "address": "EjNGK6Kvtxasr6KEjHtakRVSUSeKJfvGZaVrMp4THj8X",
    "rank": 276,
    "last24hPoints": "f4610900",
    "points": "f4610900",
    "positions": 2
  },
  {
    "address": "V4ATcVjNc1ondoDNjE6uukAeRzju1V9aFcnBTpsn8YL",
    "rank": 277,
    "last24hPoints": "ee6b2800",
    "points": "ee6b2800",
    "positions": 1
  },
  {
    "address": "BB7QHNwSo3NsscrBt95LdcQhqrgFYrhvdbzJEXJdNdKn",
    "rank": 278,
    "last24hPoints": "d693a400",
    "points": "d693a400",
    "positions": 1
  },
  {
    "address": "BwnMyQjJChz9wWcgutvAZPaD9WygjHk3sts38cx63Jwq",
    "rank": 279,
    "last24hPoints": "d09dc300",
    "points": "d09dc300",
    "positions": 1
  },
  {
    "address": "FqkdyzWWGZdrxtHij6qb9ygek93RZEyviSnDf7EfMNqP",
    "rank": 280,
    "last24hPoints": "d09dc300",
    "points": "d09dc300",
    "positions": 1
  },
  {
    "address": "3LFspBdw4iR7CL8vZS6sTDwL4HjFffCUnbthDAyBLppT",
    "rank": 281,
    "last24hPoints": "c4b20100",
    "points": "c4b20100",
    "positions": 1
  },
  {
    "address": "CkS4fpaGnr3jdUJKL9zqv7ukju5yfAia3DNuKiJB5kFU",
    "rank": 282,
    "last24hPoints": "bebc2000",
    "points": "bebc2000",
    "positions": 0
  },
  {
    "address": "CboiHc6wq98pnc17wdAt7hCUcu4bEgZRA1rsiEgSv6hT",
    "rank": 283,
    "last24hPoints": "bebc2000",
    "points": "bebc2000",
    "positions": 1
  },
  {
    "address": "B477J9jchKzS7nqvMpMkidkU9soKKnCPbYueDo9aXici",
    "rank": 284,
    "last24hPoints": "b8c63f00",
    "points": "b8c63f00",
    "positions": 1
  },
  {
    "address": "Ept9VhWUK4yvYZUuy539tpe4zy57spVLimcnztKgibsF",
    "rank": 285,
    "last24hPoints": "b2d05e00",
    "points": "b2d05e00",
    "positions": 0
  },
  {
    "address": "Fe8iXvFtG1anz6QjKeDut7sNvVQLGWSwRT1c3QoutQ75",
    "rank": 286,
    "last24hPoints": "b2d05e00",
    "points": "b2d05e00",
    "positions": 3
  },
  {
    "address": "6TSFJNbuoGAAZ2Uj9Q4SZYEafKBmUkLsJFck2rt9LRPx",
    "rank": 287,
    "last24hPoints": "acda7d00",
    "points": "acda7d00",
    "positions": 1
  },
  {
    "address": "piwUHCJw6m8cXyJvFY6Latw7mG3HVRHToyGTi8fxhcE",
    "rank": 288,
    "last24hPoints": "acda7d00",
    "points": "acda7d00",
    "positions": 1
  },
  {
    "address": "C24HUUWUoMgy1owRr7bfcg57kXDqJ1wxS6RzAwX3Ce1N",
    "rank": 289,
    "last24hPoints": "a6e49c00",
    "points": "a6e49c00",
    "positions": 1
  },
  {
    "address": "9gWBjuN7jfw9UkFPeoE19v3hJsNGYy6knNfTtznEzXnU",
    "rank": 290,
    "last24hPoints": "9af8da00",
    "points": "9af8da00",
    "positions": 1
  },
  {
    "address": "GWhArYBZBCEHgMuKSdb998Yvqnoim6b5rWXzGaUJZiY9",
    "rank": 291,
    "last24hPoints": "8f0d1800",
    "points": "8f0d1800",
    "positions": 1
  },
  {
    "address": "HYxWS1zMTMqW1AWPLG1NVuFuBue4E89bTfabvdLHCeSo",
    "rank": 292,
    "last24hPoints": "8f0d1800",
    "points": "8f0d1800",
    "positions": 1
  },
  {
    "address": "6EWgCuV2s56n45jB3vx1o9FbQDzJmW9UwAU11UhbKUfP",
    "rank": 293,
    "last24hPoints": "77359400",
    "points": "77359400",
    "positions": 1
  },
  {
    "address": "FNtUsuJfpGVDYEJxcKHRpbgWnZ8VXJWfhWFhEiFSSjQH",
    "rank": 294,
    "last24hPoints": "713fb300",
    "points": "713fb300",
    "positions": 0
  },
  {
    "address": "C5xURVz9DEwL6A41yVJ3KivutSLVVvjDrmbi9hUvuQVS",
    "rank": 295,
    "last24hPoints": "59682f00",
    "points": "59682f00",
    "positions": 0
  },
  {
    "address": "6UvRAWo3C4wnQgzsqLz7B9QUqrd5YvN7xQFtqPYLpT5i",
    "rank": 296,
    "last24hPoints": "59682f00",
    "points": "59682f00",
    "positions": 1
  },
  {
    "address": "Ah9TwBB4raodzzDSy2zEQmGsfbfkZAGcAYUnGzUMwzoQ",
    "rank": 297,
    "last24hPoints": "47868c00",
    "points": "47868c00",
    "positions": 0
  },
  {
    "address": "G3pZtE8eV2c79ML9MTRdUZ1U9Duf1SeoaphC3LqkoFsN",
    "rank": 298,
    "last24hPoints": "47868c00",
    "points": "47868c00",
    "positions": 0
  },
  {
    "address": "5BWSufbcPVWDiNKvTEybTk4XeZhbMSXttcPkJGtge6JM",
    "rank": 299,
    "last24hPoints": "47868c00",
    "points": "47868c00",
    "positions": 0
  },
  {
    "address": "GP4a5ptvW1wM2GaiQZ8oXqm7qtALi2GWFYjqYedtCVJn",
    "rank": 300,
    "last24hPoints": "47868c00",
    "points": "47868c00",
    "positions": 0
  },
  {
    "address": "GFcBFUXUrpA8xQH2WWhVgDq2NS3iSQodFLKx1CivPejx",
    "rank": 301,
    "last24hPoints": "47868c00",
    "points": "47868c00",
    "positions": 0
  },
  {
    "address": "FYERTh2JSFZqCK5WBPS7T7VX27ZXs5R3iKD23LkvPCPo",
    "rank": 302,
    "last24hPoints": "4190ab00",
    "points": "4190ab00",
    "positions": 1
  },
  {
    "address": "93hfqsExmQcuWEK16kLsMbAg5VxXLxtmvGAaTvPjUjvF",
    "rank": 303,
    "last24hPoints": "4190ab00",
    "points": "4190ab00",
    "positions": 1
  },
  {
    "address": "FBH2xusgfs3Y6f3hu3P6VYSURWWc3kY3YaZb3FzfZaHM",
    "rank": 304,
    "last24hPoints": "2faf0800",
    "points": "2faf0800",
    "positions": 0
  },
  {
    "address": "Fx6Gc84Ep5oFPjSAfoAxdDbeai4DTRwjFkAg2M7L3to5",
    "rank": 305,
    "last24hPoints": "29b92700",
    "points": "29b92700",
    "positions": 0
  },
  {
    "address": "DdygLWLyX3PKG4RasRjzedaNJyyVpFVSqbTJTnrekwdR",
    "rank": 306,
    "last24hPoints": "29b92700",
    "points": "29b92700",
    "positions": 1
  },
  {
    "address": "BTkEGcqLimgZihR6M8Hb7HHmzqKtzSPF1XVtk4EBmvuj",
    "rank": 307,
    "last24hPoints": "23c34600",
    "points": "23c34600",
    "positions": 1
  },
  {
    "address": "8fTo6seNiSDSdeeFVMdmVkGDjZsxbcFqcxqEJ84yv4V2",
    "rank": 308,
    "last24hPoints": "23c34600",
    "points": "23c34600",
    "positions": 0
  },
  {
    "address": "2aMH1A98vBTDD9B4s9dExxkPAoRFiSUUd52GfS87nuKQ",
    "rank": 309,
    "last24hPoints": "23c34600",
    "points": "23c34600",
    "positions": 1
  },
  {
    "address": "9qQSTFm9GYaagsp1envL7tedZs9cbeYKrUrqfwCFP7MP",
    "rank": 310,
    "last24hPoints": "1dcd6500",
    "points": "1dcd6500",
    "positions": 1
  },
  {
    "address": "AKSGLhAaPJtwrQ8vJUkNGgrKKczoRda3aMTo5tXJVPm4",
    "rank": 311,
    "last24hPoints": "1dcd6500",
    "points": "1dcd6500",
    "positions": 1
  },
  {
    "address": "GRZYmSFHpw6FS4oRUiyZmW54WDpLoQdXVFDXvhJaGRUv",
    "rank": 312,
    "last24hPoints": "1dcd6500",
    "points": "1dcd6500",
    "positions": 1
  },
  {
    "address": "BDJE3UtbQysj8zqto78ZaGJYDLaLztJAaXCD8ahyJNLU",
    "rank": 313,
    "last24hPoints": "17d78400",
    "points": "17d78400",
    "positions": 1
  },
  {
    "address": "CiCgPiKyYosLrTpbidsykqUmucP1qxwuz6n3ELaNLFLy",
    "rank": 314,
    "last24hPoints": "17d78400",
    "points": "17d78400",
    "positions": 1
  },
  {
    "address": "CySWqqZDsgsYKWxQc9ZwSqSFoomsrmGKTSzruqY173dc",
    "rank": 315,
    "last24hPoints": "17d78400",
    "points": "17d78400",
    "positions": 1
  },
  {
    "address": "BBVrDzBBYHR5YabhfoRatN5v2Z364c4BDVVyNDddYXp5",
    "rank": 316,
    "last24hPoints": "17d78400",
    "points": "17d78400",
    "positions": 1
  },
  {
    "address": "FUycdx1K3xD3byibACfe5c6MJFMmjuiBtgSanXibWDoi",
    "rank": 317,
    "last24hPoints": "17d78400",
    "points": "17d78400",
    "positions": 1
  },
  {
    "address": "DgNghrpHehKRBnrWpNBEQVevPD5kg7mENYVgbyqR35oW",
    "rank": 318,
    "last24hPoints": "17d78400",
    "points": "17d78400",
    "positions": 1
  },
  {
    "address": "B87uR2tp1tiBDvcMJHS9QrTqSkT274zXL8497cB5b31d",
    "rank": 319,
    "last24hPoints": "17d78400",
    "points": "17d78400",
    "positions": 1
  },
  {
    "address": "FvuzRFxaHX48rMBq7y6mGcKXf5xuccN5StqMTadpfApq",
    "rank": 320,
    "last24hPoints": "11e1a300",
    "points": "11e1a300",
    "positions": 1
  },
  {
    "address": "7S64UKWdUpvLUVB2PY9SzGmA632FWqKH7kXT6LeQCwM9",
    "rank": 321,
    "last24hPoints": "11e1a300",
    "points": "11e1a300",
    "positions": 0
  },
  {
    "address": "HhMaRsMjzPhE3LWb3Gk5PcNvvTS9Znh9kjAWAGhZYnMb",
    "rank": 322,
    "last24hPoints": "11e1a300",
    "points": "11e1a300",
    "positions": 0
  },
  {
    "address": "HsTUnM5BNoHd5ceacR5DqmM1MdxayjH1qysApkqUEwhs",
    "rank": 323,
    "last24hPoints": "11e1a300",
    "points": "11e1a300",
    "positions": 0
  },
  {
    "address": "92a1F4W8vsnvyTqzA3DYnbgxpihAWzWYhe5JpyzroZ9f",
    "rank": 324,
    "last24hPoints": "11e1a300",
    "points": "11e1a300",
    "positions": 1
  },
  {
    "address": "BqeY6rhncW7joS5K9xvtxRboqVxE3MiN1ET2JmHgxTWX",
    "rank": 325,
    "last24hPoints": "11e1a300",
    "points": "11e1a300",
    "positions": 1
  },
  {
    "address": "D59eJ17DMTwgvhAmAKMtfk5EbD73BCayeGzpBo11Xjs8",
    "rank": 326,
    "last24hPoints": "11e1a300",
    "points": "11e1a300",
    "positions": 1
  },
  {
    "address": "G4h8wjifDFQuxcvxZcB2ERk9z7jywWzSNM32bbVGTEmS",
    "rank": 327,
    "last24hPoints": "11e1a300",
    "points": "11e1a300",
    "positions": 1
  },
  {
    "address": "7ywaB9RrBfqVWdy26ezqr6WvCz55u4TfQEyHpPbgkSCk",
    "rank": 328,
    "last24hPoints": "0bebc200",
    "points": "0bebc200",
    "positions": 1
  },
  {
    "address": "5DYjgjvf9sAuH1YvXZ5svhSz1CQo1Rsp3UPjdTE3jjsB",
    "rank": 329,
    "last24hPoints": "0bebc200",
    "points": "0bebc200",
    "positions": 1
  },
  {
    "address": "HfhosCbk2xFDWf3qr4Qs6JQvAAaNXm8SYttqF8Ng4jqV",
    "rank": 330,
    "last24hPoints": "0bebc200",
    "points": "0bebc200",
    "positions": 1
  },
  {
    "address": "DH29B3PFSs4xfb3TXrBcjESHcgQzmw5TKHojV8iWrEbP",
    "rank": 331,
    "last24hPoints": "0bebc200",
    "points": "0bebc200",
    "positions": 1
  },
  {
    "address": "AAZcaNiF5WRPnVNwnWBgrN2SZXgBPZrtYQa5if9o2Tre",
    "rank": 332,
    "last24hPoints": "0bebc200",
    "points": "0bebc200",
    "positions": 1
  },
  {
    "address": "GgtjRVBi2PKcpScQHuW9nrm4mPVXgWNyTeiY78y6VrXJ",
    "rank": 333,
    "last24hPoints": "0bebc200",
    "points": "0bebc200",
    "positions": 0
  },
  {
    "address": "5PKwuytrWQpugy5u466K9ivqM2kjzVhd87qjp4TWSx9Z",
    "rank": 334,
    "last24hPoints": "0bebc200",
    "points": "0bebc200",
    "positions": 0
  },
  {
    "address": "3JVPgvP2CyzujiHimbqM8ibhc7fYmcTZQD6f6piGfyiF",
    "rank": 335,
    "last24hPoints": "0bebc200",
    "points": "0bebc200",
    "positions": 1
  },
  {
    "address": "DbQKnbCcy13WkQpsYLTxaQqJzZwSeVvFEz77KSUuFwUq",
    "rank": 336,
    "last24hPoints": "05f5e100",
    "points": "05f5e100",
    "positions": 0
  },
  {
    "address": "Cu1vPPSiiTdR5xH9EbEoTkvMfN8bPhBM4ud4uSFWvQNE",
    "rank": 337,
    "last24hPoints": "05f5e100",
    "points": "05f5e100",
    "positions": 0
  },
  {
    "address": "2PKYEYCVZ8uaLbQM5WUjAbuda6P7G5LWus2GE8EtE3Cj",
    "rank": 338,
    "last24hPoints": "05f5e100",
    "points": "05f5e100",
    "positions": 1
  },
  {
    "address": "9zoHwAkqeFCjeB1oQtfMny1nABEwxZ5AA1PH5AAgBNUW",
    "rank": 339,
    "last24hPoints": "05f5e100",
    "points": "05f5e100",
    "positions": 1
  },
  {
    "address": "4DtfcvrfNpp75oytoBx937N3r3FkPQB2X5Xe381osQDK",
    "rank": 340,
    "last24hPoints": "05f5e100",
    "points": "05f5e100",
    "positions": 2
  },
  {
    "address": "82wxZByeNcJm2sKtBLSU16WaRtr37G3ufUaKeZ5HGT7K",
    "rank": 341,
    "last24hPoints": "05f5e100",
    "points": "05f5e100",
    "positions": 1
  },
  {
    "address": "CEcTEXtChRAMNqEhyFoXHpJdsB823pY1sa9km4BDJ4zi",
    "rank": 342,
    "last24hPoints": "05f5e100",
    "points": "05f5e100",
    "positions": 0
  },
  {
    "address": "BJatLSAUNyGHKCTwCv9HA2kL7RNkdfJNaENd5XZ4hRab",
    "rank": 343,
    "last24hPoints": "05f5e100",
    "points": "05f5e100",
    "positions": 0
  },
  {
    "address": "DUq8M9b4uqAzunpdGEJPwRVQv1pEC2EMC3wGbkATFKFo",
    "rank": 344,
    "last24hPoints": "05f5e100",
    "points": "05f5e100",
    "positions": 0
  },
  {
    "address": "Cv6CDMxM3uMj2mZdHCMDL1GaP6QeK1SPxEEzJiDtEyxZ",
    "rank": 345,
    "last24hPoints": "00",
    "points": "00",
    "positions": 1
  },
  {
    "address": "DuaZHfBoRpAFoTMjjwzr1xQAWjDk4zeoGTpdGTmUA6Z5",
    "rank": 346,
    "last24hPoints": "00",
    "points": "00",
    "positions": 0
  },
  {
    "address": "8ej448DmAP6fEJ93rY3Y61wrjepToggXtgtRFdXyvr1d",
    "rank": 347,
    "last24hPoints": "00",
    "points": "00",
    "positions": 0
  },
  {
    "address": "4ajmrc2haeTkH1DdEXuQsutGSoQADaxme61dSTjGs2Ls",
    "rank": 348,
    "last24hPoints": "00",
    "points": "00",
    "positions": 0
  },
  {
    "address": "CFLS5JGeR4uyUXQb4SVthm766nd26RWM3pBjAweRZVFx",
    "rank": 349,
    "last24hPoints": "00",
    "points": "00",
    "positions": 0
  },
  {
    "address": "hHttLBFA7S7qF3Y2rdoQgyzVXUgyBsHksZyweXMn2vC",
    "rank": 350,
    "last24hPoints": "00",
    "points": "00",
    "positions": 0
  },
  {
    "address": "CLFkJzFdzQicV8hYGrMeSzDyFRqUgbxnvBhWvWjKz2Mn",
    "rank": 351,
    "last24hPoints": "00",
    "points": "00",
    "positions": 0
  },
  {
    "address": "8jPYF67a8xxm3gz3p4R5eNvjBpLxGG6ira3ZPeftRd9Y",
    "rank": 352,
    "last24hPoints": "00",
    "points": "00",
    "positions": 0
  },
  {
    "address": "HdthQPCj2DssVBphaRYgsZeNGXuJvYpu3XozZnJ1opVU",
    "rank": 353,
    "last24hPoints": "00",
    "points": "00",
    "positions": 0
  },
  {
    "address": "4JwXLWF9V9woz7kjjPZRHDAbFHJHTAGWMQpYGmLdEQYV",
    "rank": 354,
    "last24hPoints": "00",
    "points": "00",
    "positions": 1
  },
  {
    "address": "5Nsuvpip66egtzsxTcNT6xgwBMUQ8FQcN5M3uchnDuUW",
    "rank": 355,
    "last24hPoints": "00",
    "points": "00",
    "positions": 1
  },
  {
    "address": "9HqDMCf3UGsuMNPFsKN1eLiwmRTrD9YndKBKss5wcQ5R",
    "rank": 356,
    "last24hPoints": "00",
    "points": "00",
    "positions": 1
  },
  {
    "address": "8RB1Uqe7aAKkvBpPPVrCes9rsj2xvjAwKiqngZ97tMw1",
    "rank": 357,
    "last24hPoints": "00",
    "points": "00",
    "positions": 1
  },
  {
    "address": "FoBDBV1YFFmWqaRcx6kn37zECFa8sHof8byKYrFsq418",
    "rank": 358,
    "last24hPoints": "00",
    "points": "00",
    "positions": 0
  },
  {
    "address": "AwsAg9JVTr9c9ujQSBYpZ7mJ8hzMe4mxhJjpGxn7oZ2e",
    "rank": 359,
    "last24hPoints": "00",
    "points": "00",
    "positions": 1
  }
]